monthly_returns_heatmap
