Metadata-Version: 1.1
Name: monthly-returns-heatmap
Version: 0.0.4
Summary: Utility to create a monthly returns heatmap from Pandas series
Home-page: https://github.com/ranaroussi/monthly-returns-heatmap
Author: Ran Aroussi
Author-email: ran@aroussi.com
License: LGPL
Keywords: plot,heatmap,returns grid
Platform: any
Classifier: License :: OSI Approved :: GNU Lesser General Public License v3 (LGPLv3)
Classifier: Development Status :: 5 - Production/Stable
Classifier: Operating System :: OS Independent
Classifier: Intended Audience :: Developers
Classifier: Topic :: Office/Business :: Financial
Classifier: Topic :: Office/Business :: Financial :: Investment
Classifier: Topic :: Scientific/Engineering :: Interface Engine/Protocol Translator
Classifier: Topic :: Software Development :: Libraries
Classifier: Topic :: Software Development :: Libraries :: Python Modules
Classifier: Programming Language :: Python :: 3.4
Classifier: Programming Language :: Python :: 3.5
Classifier: Programming Language :: Python :: 3.6
